{
  "master": 1.0,
  "groups": {
    "weapons": 0.5,
    "bombPlant": 0.45,
    "bombDefuse": 0.45,
    "bombBeepA": 0.35,
    "bombBeepATen": 0.35,
    "bombBeepB": 0.35,
    "bombBeepBTen": 0.35,
    "c4Initiate": 0.45,
    "c4PlantFinish": 0.45,
    "c4DefuseStart": 0.45,
    "c4DefuseFinish": 0.45,
    "c4Explode": 0.45,
    "roundWin": 0.45,
    "flashExplode": 0.45,
    "smoke": 0.4,
    "smokeEmit": 0.4,
    "molotov": 0.45,
    "molotovLoop": 0.35,
    "molotovLoopFade": 0.35,
    "molotovExtinguish": 0.4,
    "heExplode": 0.45,
    "damageKevlar": 0.35,
    "damageBurn": 0.35,
    "damageHeadshot": 0.38,
    "doorOpen": 0.45
  },
  "weapons": {
    "default": 1.0,
    "distant": 1.0,
    "close": 0.4,
    "awp": 1.3,
    "pistols": 0.6
  },
  "damageCooldownMs": 500
}